[
    {
      "name": "Salon XYZ",
      "description": "Refund processed for Salon XYZ.",
      "timestamp": "2024-12-29T10:00:00Z"
    },
    {
      "name": "Salon ABC",
      "description": "Service card created for Salon ABC.",
      "timestamp": "2024-12-28T15:30:00Z"
    },
    {
      "name": "Salon 123",
      "description": "New salon verification completed.",
      "timestamp": "2024-12-27T12:15:00Z"
    },
    {
      "name": "Salon DEF",
      "description": "Refund processed for Salon DEF.",
      "timestamp": "2024-12-26T09:45:00Z"
    }
  ]
  